novagraph/.DS_Store
novagraph/__init__.py
novagraph/global.css
novagraph/novagraph.js
novagraph/novagraph.py
novagraph/__pycache__/__init__.cpython-37.pyc
novagraph/__pycache__/novagraph.cpython-37.pyc
nova_graph-0.1.3.dist-info/METADATA
nova_graph-0.1.3.dist-info/WHEEL
nova_graph-0.1.3.dist-info/top_level.txt
nova_graph-0.1.3.dist-info/RECORD
