Metadata-Version: 2.1
Name: nova-graph
Version: 0.1.3
Summary: A Python package to run NOVA Graph in your computational notebooks.
Home-page: https://github.com/poloclub/nova
Author: Jay Wang
Author-email: jayw@zijie.wang
License: MIT license
Keywords: Jupyter,JupyterLab,JupyterLab3,Visualization,Graph Visualization,Interactive Visualization
Platform: Linux
Platform: Mac OS X
Platform: Windows
Classifier: License :: OSI Approved :: MIT License
Classifier: Programming Language :: Python
Classifier: Programming Language :: Python :: 3
Classifier: Programming Language :: Python :: 3.6
Classifier: Programming Language :: Python :: 3.7
Classifier: Programming Language :: Python :: 3.8
Classifier: Programming Language :: Python :: 3.9
Classifier: Framework :: Jupyter
Classifier: Framework :: Jupyter :: JupyterLab
Classifier: Framework :: Jupyter :: JupyterLab :: 3
Requires-Python: >=3.6
Requires-Dist: ipython
